odoo8_addon_stock_product_location_sorted_by_qty-8.0.1.0.0.99.dev8-py2.7-nspkg.pth
odoo8_addon_stock_product_location_sorted_by_qty-8.0.1.0.0.99.dev8.dist-info/METADATA
odoo8_addon_stock_product_location_sorted_by_qty-8.0.1.0.0.99.dev8.dist-info/RECORD
odoo8_addon_stock_product_location_sorted_by_qty-8.0.1.0.0.99.dev8.dist-info/WHEEL
odoo8_addon_stock_product_location_sorted_by_qty-8.0.1.0.0.99.dev8.dist-info/namespace_packages.txt
odoo8_addon_stock_product_location_sorted_by_qty-8.0.1.0.0.99.dev8.dist-info/top_level.txt
odoo_addons/stock_product_location_sorted_by_qty/README.rst
odoo_addons/stock_product_location_sorted_by_qty/__init__.py
odoo_addons/stock_product_location_sorted_by_qty/__openerp__.py
odoo_addons/stock_product_location_sorted_by_qty/i18n/de.po
odoo_addons/stock_product_location_sorted_by_qty/i18n/es.po
odoo_addons/stock_product_location_sorted_by_qty/i18n/fr.po
odoo_addons/stock_product_location_sorted_by_qty/i18n/sl.po
odoo_addons/stock_product_location_sorted_by_qty/i18n/stock_product_location_sorted_by_qty.pot
odoo_addons/stock_product_location_sorted_by_qty/models/__init__.py
odoo_addons/stock_product_location_sorted_by_qty/models/stock.py
odoo_addons/stock_product_location_sorted_by_qty/static/description/icon.png
odoo_addons/stock_product_location_sorted_by_qty/static/description/stock_product_location_sorted_by_qty.png
odoo_addons/stock_product_location_sorted_by_qty/tests/__init__.py
odoo_addons/stock_product_location_sorted_by_qty/tests/test_product_location_sorted_by_qty.py
odoo_addons/stock_product_location_sorted_by_qty/views/stock_change_product_qty_view.xml
