Metadata-Version: 2.1
Name: odoo8-addon-stock-product-location-sorted-by-qty
Version: 8.0.1.0.0.99.dev8
Summary: In the update wizard of quantities for a product, sort the stock location by quantity
Home-page: http://akretion.com
Author: Akretion
Author-email: UNKNOWN
License: AGPL-3
Platform: UNKNOWN
Classifier: Programming Language :: Python
Classifier: Framework :: Odoo
Classifier: License :: OSI Approved :: GNU Affero General Public License v3
Requires-Python: ~=2.7
Requires-Dist: odoo (<9.0a,>=8.0a)
